pdm_tools/README.md
pdm_tools/main/__init__.py
pdm_tools/main/filter.py
pdm_tools/main/indicators.py
pdm_tools/main/scaler.py
pdm_tools-0.1.2.dist-info/LICENSE
pdm_tools-0.1.2.dist-info/METADATA
pdm_tools-0.1.2.dist-info/WHEEL
pdm_tools-0.1.2.dist-info/RECORD
